{
  "node": {
    "7f393a98de88821710258d221e5f6381f2ab0d277f": {
      "workers": {
        "app/page": {
          "moduleId": "(rsc)/./node_modules/next/dist/build/webpack/loaders/next-flight-action-entry-loader.js?actions=%5B%5B%22%2FUsers%2Frabibalam%2FDownloads%2Fapproved-main%2Fnode_modules%2F%40clerk%2Fnextjs%2Fdist%2Fesm%2Fapp-router%2Fkeyless-actions.js%22%2C%5B%7B%22id%22%3A%227f393a98de88821710258d221e5f6381f2ab0d277f%22%2C%22exportedName%22%3A%22createOrReadKeylessAction%22%7D%2C%7B%22id%22%3A%227f39944b5b44cb5574dd9a9c91ff4ebec6975a3e37%22%2C%22exportedName%22%3A%22deleteKeylessAction%22%7D%2C%7B%22id%22%3A%227f63dcbb9af1f5194fc448d974d4f7cc8d53036af9%22%2C%22exportedName%22%3A%22syncKeylessConfigAction%22%7D%5D%5D%5D&__client_imported__=!",
          "async": false
        },
        "app/sign-in/[[...rest]]/page": {
          "moduleId": "(rsc)/./node_modules/next/dist/build/webpack/loaders/next-flight-action-entry-loader.js?actions=%5B%5B%22%2FUsers%2Frabibalam%2FDownloads%2Fapproved-main%2Fnode_modules%2F%40clerk%2Fnextjs%2Fdist%2Fesm%2Fapp-router%2Fkeyless-actions.js%22%2C%5B%7B%22id%22%3A%227f393a98de88821710258d221e5f6381f2ab0d277f%22%2C%22exportedName%22%3A%22createOrReadKeylessAction%22%7D%2C%7B%22id%22%3A%227f39944b5b44cb5574dd9a9c91ff4ebec6975a3e37%22%2C%22exportedName%22%3A%22deleteKeylessAction%22%7D%2C%7B%22id%22%3A%227f63dcbb9af1f5194fc448d974d4f7cc8d53036af9%22%2C%22exportedName%22%3A%22syncKeylessConfigAction%22%7D%5D%5D%5D&__client_imported__=!",
          "async": false
        },
        "app/_not-found/page": {
          "moduleId": "(rsc)/./node_modules/next/dist/build/webpack/loaders/next-flight-action-entry-loader.js?actions=%5B%5B%22%2FUsers%2Frabibalam%2FDownloads%2Fapproved-main%2Fnode_modules%2F%40clerk%2Fnextjs%2Fdist%2Fesm%2Fapp-router%2Fkeyless-actions.js%22%2C%5B%7B%22id%22%3A%227f393a98de88821710258d221e5f6381f2ab0d277f%22%2C%22exportedName%22%3A%22createOrReadKeylessAction%22%7D%2C%7B%22id%22%3A%227f39944b5b44cb5574dd9a9c91ff4ebec6975a3e37%22%2C%22exportedName%22%3A%22deleteKeylessAction%22%7D%2C%7B%22id%22%3A%227f63dcbb9af1f5194fc448d974d4f7cc8d53036af9%22%2C%22exportedName%22%3A%22syncKeylessConfigAction%22%7D%5D%5D%5D&__client_imported__=!",
          "async": false
        },
        "app/upload/page": {
          "moduleId": "(rsc)/./node_modules/next/dist/build/webpack/loaders/next-flight-action-entry-loader.js?actions=%5B%5B%22%2FUsers%2Frabibalam%2FDownloads%2Fapproved-main%2Fnode_modules%2F%40clerk%2Fnextjs%2Fdist%2Fesm%2Fapp-router%2Fkeyless-actions.js%22%2C%5B%7B%22id%22%3A%227f393a98de88821710258d221e5f6381f2ab0d277f%22%2C%22exportedName%22%3A%22createOrReadKeylessAction%22%7D%2C%7B%22id%22%3A%227f39944b5b44cb5574dd9a9c91ff4ebec6975a3e37%22%2C%22exportedName%22%3A%22deleteKeylessAction%22%7D%2C%7B%22id%22%3A%227f63dcbb9af1f5194fc448d974d4f7cc8d53036af9%22%2C%22exportedName%22%3A%22syncKeylessConfigAction%22%7D%5D%5D%5D&__client_imported__=!",
          "async": false
        },
        "app/review/page": {
          "moduleId": "(rsc)/./node_modules/next/dist/build/webpack/loaders/next-flight-action-entry-loader.js?actions=%5B%5B%22%2FUsers%2Frabibalam%2FDownloads%2Fapproved-main%2Fnode_modules%2F%40clerk%2Fnextjs%2Fdist%2Fesm%2Fapp-router%2Fkeyless-actions.js%22%2C%5B%7B%22id%22%3A%227f393a98de88821710258d221e5f6381f2ab0d277f%22%2C%22exportedName%22%3A%22createOrReadKeylessAction%22%7D%2C%7B%22id%22%3A%227f39944b5b44cb5574dd9a9c91ff4ebec6975a3e37%22%2C%22exportedName%22%3A%22deleteKeylessAction%22%7D%2C%7B%22id%22%3A%227f63dcbb9af1f5194fc448d974d4f7cc8d53036af9%22%2C%22exportedName%22%3A%22syncKeylessConfigAction%22%7D%5D%5D%5D&__client_imported__=!",
          "async": false
        },
        "app/debug/page": {
          "moduleId": "(rsc)/./node_modules/next/dist/build/webpack/loaders/next-flight-action-entry-loader.js?actions=%5B%5B%22%2FUsers%2Frabibalam%2FDownloads%2Fapproved-main%2Fnode_modules%2F%40clerk%2Fnextjs%2Fdist%2Fesm%2Fapp-router%2Fkeyless-actions.js%22%2C%5B%7B%22id%22%3A%227f393a98de88821710258d221e5f6381f2ab0d277f%22%2C%22exportedName%22%3A%22createOrReadKeylessAction%22%7D%2C%7B%22id%22%3A%227f39944b5b44cb5574dd9a9c91ff4ebec6975a3e37%22%2C%22exportedName%22%3A%22deleteKeylessAction%22%7D%2C%7B%22id%22%3A%227f63dcbb9af1f5194fc448d974d4f7cc8d53036af9%22%2C%22exportedName%22%3A%22syncKeylessConfigAction%22%7D%5D%5D%5D&__client_imported__=!",
          "async": false
        }
      },
      "layer": {
        "app/page": "rsc",
        "app/sign-in/[[...rest]]/page": "rsc",
        "app/_not-found/page": "rsc",
        "app/upload/page": "rsc",
        "app/review/page": "rsc",
        "app/debug/page": "rsc"
      }
    },
    "7f39944b5b44cb5574dd9a9c91ff4ebec6975a3e37": {
      "workers": {
        "app/page": {
          "moduleId": "(rsc)/./node_modules/next/dist/build/webpack/loaders/next-flight-action-entry-loader.js?actions=%5B%5B%22%2FUsers%2Frabibalam%2FDownloads%2Fapproved-main%2Fnode_modules%2F%40clerk%2Fnextjs%2Fdist%2Fesm%2Fapp-router%2Fkeyless-actions.js%22%2C%5B%7B%22id%22%3A%227f393a98de88821710258d221e5f6381f2ab0d277f%22%2C%22exportedName%22%3A%22createOrReadKeylessAction%22%7D%2C%7B%22id%22%3A%227f39944b5b44cb5574dd9a9c91ff4ebec6975a3e37%22%2C%22exportedName%22%3A%22deleteKeylessAction%22%7D%2C%7B%22id%22%3A%227f63dcbb9af1f5194fc448d974d4f7cc8d53036af9%22%2C%22exportedName%22%3A%22syncKeylessConfigAction%22%7D%5D%5D%5D&__client_imported__=!",
          "async": false
        },
        "app/sign-in/[[...rest]]/page": {
          "moduleId": "(rsc)/./node_modules/next/dist/build/webpack/loaders/next-flight-action-entry-loader.js?actions=%5B%5B%22%2FUsers%2Frabibalam%2FDownloads%2Fapproved-main%2Fnode_modules%2F%40clerk%2Fnextjs%2Fdist%2Fesm%2Fapp-router%2Fkeyless-actions.js%22%2C%5B%7B%22id%22%3A%227f393a98de88821710258d221e5f6381f2ab0d277f%22%2C%22exportedName%22%3A%22createOrReadKeylessAction%22%7D%2C%7B%22id%22%3A%227f39944b5b44cb5574dd9a9c91ff4ebec6975a3e37%22%2C%22exportedName%22%3A%22deleteKeylessAction%22%7D%2C%7B%22id%22%3A%227f63dcbb9af1f5194fc448d974d4f7cc8d53036af9%22%2C%22exportedName%22%3A%22syncKeylessConfigAction%22%7D%5D%5D%5D&__client_imported__=!",
          "async": false
        },
        "app/_not-found/page": {
          "moduleId": "(rsc)/./node_modules/next/dist/build/webpack/loaders/next-flight-action-entry-loader.js?actions=%5B%5B%22%2FUsers%2Frabibalam%2FDownloads%2Fapproved-main%2Fnode_modules%2F%40clerk%2Fnextjs%2Fdist%2Fesm%2Fapp-router%2Fkeyless-actions.js%22%2C%5B%7B%22id%22%3A%227f393a98de88821710258d221e5f6381f2ab0d277f%22%2C%22exportedName%22%3A%22createOrReadKeylessAction%22%7D%2C%7B%22id%22%3A%227f39944b5b44cb5574dd9a9c91ff4ebec6975a3e37%22%2C%22exportedName%22%3A%22deleteKeylessAction%22%7D%2C%7B%22id%22%3A%227f63dcbb9af1f5194fc448d974d4f7cc8d53036af9%22%2C%22exportedName%22%3A%22syncKeylessConfigAction%22%7D%5D%5D%5D&__client_imported__=!",
          "async": false
        },
        "app/upload/page": {
          "moduleId": "(rsc)/./node_modules/next/dist/build/webpack/loaders/next-flight-action-entry-loader.js?actions=%5B%5B%22%2FUsers%2Frabibalam%2FDownloads%2Fapproved-main%2Fnode_modules%2F%40clerk%2Fnextjs%2Fdist%2Fesm%2Fapp-router%2Fkeyless-actions.js%22%2C%5B%7B%22id%22%3A%227f393a98de88821710258d221e5f6381f2ab0d277f%22%2C%22exportedName%22%3A%22createOrReadKeylessAction%22%7D%2C%7B%22id%22%3A%227f39944b5b44cb5574dd9a9c91ff4ebec6975a3e37%22%2C%22exportedName%22%3A%22deleteKeylessAction%22%7D%2C%7B%22id%22%3A%227f63dcbb9af1f5194fc448d974d4f7cc8d53036af9%22%2C%22exportedName%22%3A%22syncKeylessConfigAction%22%7D%5D%5D%5D&__client_imported__=!",
          "async": false
        },
        "app/review/page": {
          "moduleId": "(rsc)/./node_modules/next/dist/build/webpack/loaders/next-flight-action-entry-loader.js?actions=%5B%5B%22%2FUsers%2Frabibalam%2FDownloads%2Fapproved-main%2Fnode_modules%2F%40clerk%2Fnextjs%2Fdist%2Fesm%2Fapp-router%2Fkeyless-actions.js%22%2C%5B%7B%22id%22%3A%227f393a98de88821710258d221e5f6381f2ab0d277f%22%2C%22exportedName%22%3A%22createOrReadKeylessAction%22%7D%2C%7B%22id%22%3A%227f39944b5b44cb5574dd9a9c91ff4ebec6975a3e37%22%2C%22exportedName%22%3A%22deleteKeylessAction%22%7D%2C%7B%22id%22%3A%227f63dcbb9af1f5194fc448d974d4f7cc8d53036af9%22%2C%22exportedName%22%3A%22syncKeylessConfigAction%22%7D%5D%5D%5D&__client_imported__=!",
          "async": false
        },
        "app/debug/page": {
          "moduleId": "(rsc)/./node_modules/next/dist/build/webpack/loaders/next-flight-action-entry-loader.js?actions=%5B%5B%22%2FUsers%2Frabibalam%2FDownloads%2Fapproved-main%2Fnode_modules%2F%40clerk%2Fnextjs%2Fdist%2Fesm%2Fapp-router%2Fkeyless-actions.js%22%2C%5B%7B%22id%22%3A%227f393a98de88821710258d221e5f6381f2ab0d277f%22%2C%22exportedName%22%3A%22createOrReadKeylessAction%22%7D%2C%7B%22id%22%3A%227f39944b5b44cb5574dd9a9c91ff4ebec6975a3e37%22%2C%22exportedName%22%3A%22deleteKeylessAction%22%7D%2C%7B%22id%22%3A%227f63dcbb9af1f5194fc448d974d4f7cc8d53036af9%22%2C%22exportedName%22%3A%22syncKeylessConfigAction%22%7D%5D%5D%5D&__client_imported__=!",
          "async": false
        }
      },
      "layer": {
        "app/page": "rsc",
        "app/sign-in/[[...rest]]/page": "rsc",
        "app/_not-found/page": "rsc",
        "app/upload/page": "rsc",
        "app/review/page": "rsc",
        "app/debug/page": "rsc"
      }
    },
    "7f63dcbb9af1f5194fc448d974d4f7cc8d53036af9": {
      "workers": {
        "app/page": {
          "moduleId": "(rsc)/./node_modules/next/dist/build/webpack/loaders/next-flight-action-entry-loader.js?actions=%5B%5B%22%2FUsers%2Frabibalam%2FDownloads%2Fapproved-main%2Fnode_modules%2F%40clerk%2Fnextjs%2Fdist%2Fesm%2Fapp-router%2Fkeyless-actions.js%22%2C%5B%7B%22id%22%3A%227f393a98de88821710258d221e5f6381f2ab0d277f%22%2C%22exportedName%22%3A%22createOrReadKeylessAction%22%7D%2C%7B%22id%22%3A%227f39944b5b44cb5574dd9a9c91ff4ebec6975a3e37%22%2C%22exportedName%22%3A%22deleteKeylessAction%22%7D%2C%7B%22id%22%3A%227f63dcbb9af1f5194fc448d974d4f7cc8d53036af9%22%2C%22exportedName%22%3A%22syncKeylessConfigAction%22%7D%5D%5D%5D&__client_imported__=!",
          "async": false
        },
        "app/sign-in/[[...rest]]/page": {
          "moduleId": "(rsc)/./node_modules/next/dist/build/webpack/loaders/next-flight-action-entry-loader.js?actions=%5B%5B%22%2FUsers%2Frabibalam%2FDownloads%2Fapproved-main%2Fnode_modules%2F%40clerk%2Fnextjs%2Fdist%2Fesm%2Fapp-router%2Fkeyless-actions.js%22%2C%5B%7B%22id%22%3A%227f393a98de88821710258d221e5f6381f2ab0d277f%22%2C%22exportedName%22%3A%22createOrReadKeylessAction%22%7D%2C%7B%22id%22%3A%227f39944b5b44cb5574dd9a9c91ff4ebec6975a3e37%22%2C%22exportedName%22%3A%22deleteKeylessAction%22%7D%2C%7B%22id%22%3A%227f63dcbb9af1f5194fc448d974d4f7cc8d53036af9%22%2C%22exportedName%22%3A%22syncKeylessConfigAction%22%7D%5D%5D%5D&__client_imported__=!",
          "async": false
        },
        "app/_not-found/page": {
          "moduleId": "(rsc)/./node_modules/next/dist/build/webpack/loaders/next-flight-action-entry-loader.js?actions=%5B%5B%22%2FUsers%2Frabibalam%2FDownloads%2Fapproved-main%2Fnode_modules%2F%40clerk%2Fnextjs%2Fdist%2Fesm%2Fapp-router%2Fkeyless-actions.js%22%2C%5B%7B%22id%22%3A%227f393a98de88821710258d221e5f6381f2ab0d277f%22%2C%22exportedName%22%3A%22createOrReadKeylessAction%22%7D%2C%7B%22id%22%3A%227f39944b5b44cb5574dd9a9c91ff4ebec6975a3e37%22%2C%22exportedName%22%3A%22deleteKeylessAction%22%7D%2C%7B%22id%22%3A%227f63dcbb9af1f5194fc448d974d4f7cc8d53036af9%22%2C%22exportedName%22%3A%22syncKeylessConfigAction%22%7D%5D%5D%5D&__client_imported__=!",
          "async": false
        },
        "app/upload/page": {
          "moduleId": "(rsc)/./node_modules/next/dist/build/webpack/loaders/next-flight-action-entry-loader.js?actions=%5B%5B%22%2FUsers%2Frabibalam%2FDownloads%2Fapproved-main%2Fnode_modules%2F%40clerk%2Fnextjs%2Fdist%2Fesm%2Fapp-router%2Fkeyless-actions.js%22%2C%5B%7B%22id%22%3A%227f393a98de88821710258d221e5f6381f2ab0d277f%22%2C%22exportedName%22%3A%22createOrReadKeylessAction%22%7D%2C%7B%22id%22%3A%227f39944b5b44cb5574dd9a9c91ff4ebec6975a3e37%22%2C%22exportedName%22%3A%22deleteKeylessAction%22%7D%2C%7B%22id%22%3A%227f63dcbb9af1f5194fc448d974d4f7cc8d53036af9%22%2C%22exportedName%22%3A%22syncKeylessConfigAction%22%7D%5D%5D%5D&__client_imported__=!",
          "async": false
        },
        "app/review/page": {
          "moduleId": "(rsc)/./node_modules/next/dist/build/webpack/loaders/next-flight-action-entry-loader.js?actions=%5B%5B%22%2FUsers%2Frabibalam%2FDownloads%2Fapproved-main%2Fnode_modules%2F%40clerk%2Fnextjs%2Fdist%2Fesm%2Fapp-router%2Fkeyless-actions.js%22%2C%5B%7B%22id%22%3A%227f393a98de88821710258d221e5f6381f2ab0d277f%22%2C%22exportedName%22%3A%22createOrReadKeylessAction%22%7D%2C%7B%22id%22%3A%227f39944b5b44cb5574dd9a9c91ff4ebec6975a3e37%22%2C%22exportedName%22%3A%22deleteKeylessAction%22%7D%2C%7B%22id%22%3A%227f63dcbb9af1f5194fc448d974d4f7cc8d53036af9%22%2C%22exportedName%22%3A%22syncKeylessConfigAction%22%7D%5D%5D%5D&__client_imported__=!",
          "async": false
        },
        "app/debug/page": {
          "moduleId": "(rsc)/./node_modules/next/dist/build/webpack/loaders/next-flight-action-entry-loader.js?actions=%5B%5B%22%2FUsers%2Frabibalam%2FDownloads%2Fapproved-main%2Fnode_modules%2F%40clerk%2Fnextjs%2Fdist%2Fesm%2Fapp-router%2Fkeyless-actions.js%22%2C%5B%7B%22id%22%3A%227f393a98de88821710258d221e5f6381f2ab0d277f%22%2C%22exportedName%22%3A%22createOrReadKeylessAction%22%7D%2C%7B%22id%22%3A%227f39944b5b44cb5574dd9a9c91ff4ebec6975a3e37%22%2C%22exportedName%22%3A%22deleteKeylessAction%22%7D%2C%7B%22id%22%3A%227f63dcbb9af1f5194fc448d974d4f7cc8d53036af9%22%2C%22exportedName%22%3A%22syncKeylessConfigAction%22%7D%5D%5D%5D&__client_imported__=!",
          "async": false
        }
      },
      "layer": {
        "app/page": "rsc",
        "app/sign-in/[[...rest]]/page": "rsc",
        "app/_not-found/page": "rsc",
        "app/upload/page": "rsc",
        "app/review/page": "rsc",
        "app/debug/page": "rsc"
      }
    },
    "7fd62658a41224c9667c72a0b82c71390b1a333135": {
      "workers": {
        "app/page": {
          "moduleId": "(action-browser)/./node_modules/next/dist/build/webpack/loaders/next-flight-action-entry-loader.js?actions=%5B%5B%22%2FUsers%2Frabibalam%2FDownloads%2Fapproved-main%2Fnode_modules%2F%40clerk%2Fnextjs%2Fdist%2Fesm%2Fapp-router%2Fserver-actions.js%22%2C%5B%7B%22id%22%3A%227fd62658a41224c9667c72a0b82c71390b1a333135%22%2C%22exportedName%22%3A%22invalidateCacheAction%22%7D%5D%5D%5D&__client_imported__=true!",
          "async": false
        },
        "app/sign-in/[[...rest]]/page": {
          "moduleId": "(action-browser)/./node_modules/next/dist/build/webpack/loaders/next-flight-action-entry-loader.js?actions=%5B%5B%22%2FUsers%2Frabibalam%2FDownloads%2Fapproved-main%2Fnode_modules%2F%40clerk%2Fnextjs%2Fdist%2Fesm%2Fapp-router%2Fserver-actions.js%22%2C%5B%7B%22id%22%3A%227fd62658a41224c9667c72a0b82c71390b1a333135%22%2C%22exportedName%22%3A%22invalidateCacheAction%22%7D%5D%5D%5D&__client_imported__=true!",
          "async": false
        },
        "app/_not-found/page": {
          "moduleId": "(action-browser)/./node_modules/next/dist/build/webpack/loaders/next-flight-action-entry-loader.js?actions=%5B%5B%22%2FUsers%2Frabibalam%2FDownloads%2Fapproved-main%2Fnode_modules%2F%40clerk%2Fnextjs%2Fdist%2Fesm%2Fapp-router%2Fserver-actions.js%22%2C%5B%7B%22id%22%3A%227fd62658a41224c9667c72a0b82c71390b1a333135%22%2C%22exportedName%22%3A%22invalidateCacheAction%22%7D%5D%5D%5D&__client_imported__=true!",
          "async": false
        },
        "app/upload/page": {
          "moduleId": "(action-browser)/./node_modules/next/dist/build/webpack/loaders/next-flight-action-entry-loader.js?actions=%5B%5B%22%2FUsers%2Frabibalam%2FDownloads%2Fapproved-main%2Fnode_modules%2F%40clerk%2Fnextjs%2Fdist%2Fesm%2Fapp-router%2Fserver-actions.js%22%2C%5B%7B%22id%22%3A%227fd62658a41224c9667c72a0b82c71390b1a333135%22%2C%22exportedName%22%3A%22invalidateCacheAction%22%7D%5D%5D%2C%5B%22%2FUsers%2Frabibalam%2FDownloads%2Fapproved-main%2Fsrc%2Factions%2Fupload-actions.ts%22%2C%5B%7B%22id%22%3A%2240332f7f29c19b4e9fff6c50f360b01bad72b27281%22%2C%22exportedName%22%3A%22uploadDocument%22%7D%2C%7B%22id%22%3A%2240591b2b340e10fb91ee7060d352c63647957458d5%22%2C%22exportedName%22%3A%22deleteDocument%22%7D%2C%7B%22id%22%3A%22406085d2a9b7a77a97cabb7de9cdae709854d13ff1%22%2C%22exportedName%22%3A%22getDocumentUrl%22%7D%2C%7B%22id%22%3A%224090bff9be05f54f55e2863d4209e8713e149ae547%22%2C%22exportedName%22%3A%22getDocuments%22%7D%2C%7B%22id%22%3A%2240caa720357df62a3cdce122c5bf15f57de553282b%22%2C%22exportedName%22%3A%22getDocument%22%7D%5D%5D%5D&__client_imported__=true!",
          "async": false
        },
        "app/review/page": {
          "moduleId": "(action-browser)/./node_modules/next/dist/build/webpack/loaders/next-flight-action-entry-loader.js?actions=%5B%5B%22%2FUsers%2Frabibalam%2FDownloads%2Fapproved-main%2Fnode_modules%2F%40clerk%2Fnextjs%2Fdist%2Fesm%2Fapp-router%2Fserver-actions.js%22%2C%5B%7B%22id%22%3A%227fd62658a41224c9667c72a0b82c71390b1a333135%22%2C%22exportedName%22%3A%22invalidateCacheAction%22%7D%5D%5D%5D&__client_imported__=true!",
          "async": false
        },
        "app/debug/page": {
          "moduleId": "(action-browser)/./node_modules/next/dist/build/webpack/loaders/next-flight-action-entry-loader.js?actions=%5B%5B%22%2FUsers%2Frabibalam%2FDownloads%2Fapproved-main%2Fnode_modules%2F%40clerk%2Fnextjs%2Fdist%2Fesm%2Fapp-router%2Fserver-actions.js%22%2C%5B%7B%22id%22%3A%227fd62658a41224c9667c72a0b82c71390b1a333135%22%2C%22exportedName%22%3A%22invalidateCacheAction%22%7D%5D%5D%2C%5B%22%2FUsers%2Frabibalam%2FDownloads%2Fapproved-main%2Fsrc%2Factions%2Fdebug-actions.ts%22%2C%5B%7B%22id%22%3A%22002f4b96fa015b5e7631a93d678ccd881fbe444686%22%2C%22exportedName%22%3A%22testAIExtraction%22%7D%2C%7B%22id%22%3A%220033f2162d31a669790352a3a56b8afd96f4e4a15e%22%2C%22exportedName%22%3A%22debugDocuments%22%7D%5D%5D%2C%5B%22%2FUsers%2Frabibalam%2FDownloads%2Fapproved-main%2Fsrc%2Factions%2Fdebug-pdf.ts%22%2C%5B%7B%22id%22%3A%22002443ea3c5aaf566012ecc2982841d97404e5c95e%22%2C%22exportedName%22%3A%22debugPDFExtraction%22%7D%5D%5D%5D&__client_imported__=true!",
          "async": false
        }
      },
      "layer": {
        "app/page": "action-browser",
        "app/sign-in/[[...rest]]/page": "action-browser",
        "app/_not-found/page": "action-browser",
        "app/upload/page": "action-browser",
        "app/review/page": "action-browser",
        "app/debug/page": "action-browser"
      }
    },
    "40332f7f29c19b4e9fff6c50f360b01bad72b27281": {
      "workers": {
        "app/upload/page": {
          "moduleId": "(action-browser)/./node_modules/next/dist/build/webpack/loaders/next-flight-action-entry-loader.js?actions=%5B%5B%22%2FUsers%2Frabibalam%2FDownloads%2Fapproved-main%2Fnode_modules%2F%40clerk%2Fnextjs%2Fdist%2Fesm%2Fapp-router%2Fserver-actions.js%22%2C%5B%7B%22id%22%3A%227fd62658a41224c9667c72a0b82c71390b1a333135%22%2C%22exportedName%22%3A%22invalidateCacheAction%22%7D%5D%5D%2C%5B%22%2FUsers%2Frabibalam%2FDownloads%2Fapproved-main%2Fsrc%2Factions%2Fupload-actions.ts%22%2C%5B%7B%22id%22%3A%2240332f7f29c19b4e9fff6c50f360b01bad72b27281%22%2C%22exportedName%22%3A%22uploadDocument%22%7D%2C%7B%22id%22%3A%2240591b2b340e10fb91ee7060d352c63647957458d5%22%2C%22exportedName%22%3A%22deleteDocument%22%7D%2C%7B%22id%22%3A%22406085d2a9b7a77a97cabb7de9cdae709854d13ff1%22%2C%22exportedName%22%3A%22getDocumentUrl%22%7D%2C%7B%22id%22%3A%224090bff9be05f54f55e2863d4209e8713e149ae547%22%2C%22exportedName%22%3A%22getDocuments%22%7D%2C%7B%22id%22%3A%2240caa720357df62a3cdce122c5bf15f57de553282b%22%2C%22exportedName%22%3A%22getDocument%22%7D%5D%5D%5D&__client_imported__=true!",
          "async": false
        },
        "app/review/page": {
          "moduleId": "(action-browser)/./node_modules/next/dist/build/webpack/loaders/next-flight-action-entry-loader.js?actions=%5B%5B%22%2FUsers%2Frabibalam%2FDownloads%2Fapproved-main%2Fnode_modules%2F%40clerk%2Fnextjs%2Fdist%2Fesm%2Fapp-router%2Fserver-actions.js%22%2C%5B%7B%22id%22%3A%227fd62658a41224c9667c72a0b82c71390b1a333135%22%2C%22exportedName%22%3A%22invalidateCacheAction%22%7D%5D%5D%5D&__client_imported__=true!",
          "async": false
        }
      },
      "layer": {
        "app/upload/page": "action-browser",
        "app/review/page": "action-browser"
      }
    },
    "40591b2b340e10fb91ee7060d352c63647957458d5": {
      "workers": {
        "app/upload/page": {
          "moduleId": "(action-browser)/./node_modules/next/dist/build/webpack/loaders/next-flight-action-entry-loader.js?actions=%5B%5B%22%2FUsers%2Frabibalam%2FDownloads%2Fapproved-main%2Fnode_modules%2F%40clerk%2Fnextjs%2Fdist%2Fesm%2Fapp-router%2Fserver-actions.js%22%2C%5B%7B%22id%22%3A%227fd62658a41224c9667c72a0b82c71390b1a333135%22%2C%22exportedName%22%3A%22invalidateCacheAction%22%7D%5D%5D%2C%5B%22%2FUsers%2Frabibalam%2FDownloads%2Fapproved-main%2Fsrc%2Factions%2Fupload-actions.ts%22%2C%5B%7B%22id%22%3A%2240332f7f29c19b4e9fff6c50f360b01bad72b27281%22%2C%22exportedName%22%3A%22uploadDocument%22%7D%2C%7B%22id%22%3A%2240591b2b340e10fb91ee7060d352c63647957458d5%22%2C%22exportedName%22%3A%22deleteDocument%22%7D%2C%7B%22id%22%3A%22406085d2a9b7a77a97cabb7de9cdae709854d13ff1%22%2C%22exportedName%22%3A%22getDocumentUrl%22%7D%2C%7B%22id%22%3A%224090bff9be05f54f55e2863d4209e8713e149ae547%22%2C%22exportedName%22%3A%22getDocuments%22%7D%2C%7B%22id%22%3A%2240caa720357df62a3cdce122c5bf15f57de553282b%22%2C%22exportedName%22%3A%22getDocument%22%7D%5D%5D%5D&__client_imported__=true!",
          "async": false
        },
        "app/review/page": {
          "moduleId": "(action-browser)/./node_modules/next/dist/build/webpack/loaders/next-flight-action-entry-loader.js?actions=%5B%5B%22%2FUsers%2Frabibalam%2FDownloads%2Fapproved-main%2Fnode_modules%2F%40clerk%2Fnextjs%2Fdist%2Fesm%2Fapp-router%2Fserver-actions.js%22%2C%5B%7B%22id%22%3A%227fd62658a41224c9667c72a0b82c71390b1a333135%22%2C%22exportedName%22%3A%22invalidateCacheAction%22%7D%5D%5D%5D&__client_imported__=true!",
          "async": false
        }
      },
      "layer": {
        "app/upload/page": "action-browser",
        "app/review/page": "action-browser"
      }
    },
    "406085d2a9b7a77a97cabb7de9cdae709854d13ff1": {
      "workers": {
        "app/upload/page": {
          "moduleId": "(action-browser)/./node_modules/next/dist/build/webpack/loaders/next-flight-action-entry-loader.js?actions=%5B%5B%22%2FUsers%2Frabibalam%2FDownloads%2Fapproved-main%2Fnode_modules%2F%40clerk%2Fnextjs%2Fdist%2Fesm%2Fapp-router%2Fserver-actions.js%22%2C%5B%7B%22id%22%3A%227fd62658a41224c9667c72a0b82c71390b1a333135%22%2C%22exportedName%22%3A%22invalidateCacheAction%22%7D%5D%5D%2C%5B%22%2FUsers%2Frabibalam%2FDownloads%2Fapproved-main%2Fsrc%2Factions%2Fupload-actions.ts%22%2C%5B%7B%22id%22%3A%2240332f7f29c19b4e9fff6c50f360b01bad72b27281%22%2C%22exportedName%22%3A%22uploadDocument%22%7D%2C%7B%22id%22%3A%2240591b2b340e10fb91ee7060d352c63647957458d5%22%2C%22exportedName%22%3A%22deleteDocument%22%7D%2C%7B%22id%22%3A%22406085d2a9b7a77a97cabb7de9cdae709854d13ff1%22%2C%22exportedName%22%3A%22getDocumentUrl%22%7D%2C%7B%22id%22%3A%224090bff9be05f54f55e2863d4209e8713e149ae547%22%2C%22exportedName%22%3A%22getDocuments%22%7D%2C%7B%22id%22%3A%2240caa720357df62a3cdce122c5bf15f57de553282b%22%2C%22exportedName%22%3A%22getDocument%22%7D%5D%5D%5D&__client_imported__=true!",
          "async": false
        },
        "app/review/page": {
          "moduleId": "(action-browser)/./node_modules/next/dist/build/webpack/loaders/next-flight-action-entry-loader.js?actions=%5B%5B%22%2FUsers%2Frabibalam%2FDownloads%2Fapproved-main%2Fnode_modules%2F%40clerk%2Fnextjs%2Fdist%2Fesm%2Fapp-router%2Fserver-actions.js%22%2C%5B%7B%22id%22%3A%227fd62658a41224c9667c72a0b82c71390b1a333135%22%2C%22exportedName%22%3A%22invalidateCacheAction%22%7D%5D%5D%5D&__client_imported__=true!",
          "async": false
        }
      },
      "layer": {
        "app/upload/page": "action-browser",
        "app/review/page": "action-browser"
      }
    },
    "4090bff9be05f54f55e2863d4209e8713e149ae547": {
      "workers": {
        "app/upload/page": {
          "moduleId": "(action-browser)/./node_modules/next/dist/build/webpack/loaders/next-flight-action-entry-loader.js?actions=%5B%5B%22%2FUsers%2Frabibalam%2FDownloads%2Fapproved-main%2Fnode_modules%2F%40clerk%2Fnextjs%2Fdist%2Fesm%2Fapp-router%2Fserver-actions.js%22%2C%5B%7B%22id%22%3A%227fd62658a41224c9667c72a0b82c71390b1a333135%22%2C%22exportedName%22%3A%22invalidateCacheAction%22%7D%5D%5D%2C%5B%22%2FUsers%2Frabibalam%2FDownloads%2Fapproved-main%2Fsrc%2Factions%2Fupload-actions.ts%22%2C%5B%7B%22id%22%3A%2240332f7f29c19b4e9fff6c50f360b01bad72b27281%22%2C%22exportedName%22%3A%22uploadDocument%22%7D%2C%7B%22id%22%3A%2240591b2b340e10fb91ee7060d352c63647957458d5%22%2C%22exportedName%22%3A%22deleteDocument%22%7D%2C%7B%22id%22%3A%22406085d2a9b7a77a97cabb7de9cdae709854d13ff1%22%2C%22exportedName%22%3A%22getDocumentUrl%22%7D%2C%7B%22id%22%3A%224090bff9be05f54f55e2863d4209e8713e149ae547%22%2C%22exportedName%22%3A%22getDocuments%22%7D%2C%7B%22id%22%3A%2240caa720357df62a3cdce122c5bf15f57de553282b%22%2C%22exportedName%22%3A%22getDocument%22%7D%5D%5D%5D&__client_imported__=true!",
          "async": false
        },
        "app/review/page": {
          "moduleId": "(action-browser)/./node_modules/next/dist/build/webpack/loaders/next-flight-action-entry-loader.js?actions=%5B%5B%22%2FUsers%2Frabibalam%2FDownloads%2Fapproved-main%2Fnode_modules%2F%40clerk%2Fnextjs%2Fdist%2Fesm%2Fapp-router%2Fserver-actions.js%22%2C%5B%7B%22id%22%3A%227fd62658a41224c9667c72a0b82c71390b1a333135%22%2C%22exportedName%22%3A%22invalidateCacheAction%22%7D%5D%5D%5D&__client_imported__=true!",
          "async": false
        }
      },
      "layer": {
        "app/upload/page": "action-browser",
        "app/review/page": "action-browser"
      }
    },
    "40caa720357df62a3cdce122c5bf15f57de553282b": {
      "workers": {
        "app/upload/page": {
          "moduleId": "(action-browser)/./node_modules/next/dist/build/webpack/loaders/next-flight-action-entry-loader.js?actions=%5B%5B%22%2FUsers%2Frabibalam%2FDownloads%2Fapproved-main%2Fnode_modules%2F%40clerk%2Fnextjs%2Fdist%2Fesm%2Fapp-router%2Fserver-actions.js%22%2C%5B%7B%22id%22%3A%227fd62658a41224c9667c72a0b82c71390b1a333135%22%2C%22exportedName%22%3A%22invalidateCacheAction%22%7D%5D%5D%2C%5B%22%2FUsers%2Frabibalam%2FDownloads%2Fapproved-main%2Fsrc%2Factions%2Fupload-actions.ts%22%2C%5B%7B%22id%22%3A%2240332f7f29c19b4e9fff6c50f360b01bad72b27281%22%2C%22exportedName%22%3A%22uploadDocument%22%7D%2C%7B%22id%22%3A%2240591b2b340e10fb91ee7060d352c63647957458d5%22%2C%22exportedName%22%3A%22deleteDocument%22%7D%2C%7B%22id%22%3A%22406085d2a9b7a77a97cabb7de9cdae709854d13ff1%22%2C%22exportedName%22%3A%22getDocumentUrl%22%7D%2C%7B%22id%22%3A%224090bff9be05f54f55e2863d4209e8713e149ae547%22%2C%22exportedName%22%3A%22getDocuments%22%7D%2C%7B%22id%22%3A%2240caa720357df62a3cdce122c5bf15f57de553282b%22%2C%22exportedName%22%3A%22getDocument%22%7D%5D%5D%5D&__client_imported__=true!",
          "async": false
        },
        "app/review/page": {
          "moduleId": "(action-browser)/./node_modules/next/dist/build/webpack/loaders/next-flight-action-entry-loader.js?actions=%5B%5B%22%2FUsers%2Frabibalam%2FDownloads%2Fapproved-main%2Fnode_modules%2F%40clerk%2Fnextjs%2Fdist%2Fesm%2Fapp-router%2Fserver-actions.js%22%2C%5B%7B%22id%22%3A%227fd62658a41224c9667c72a0b82c71390b1a333135%22%2C%22exportedName%22%3A%22invalidateCacheAction%22%7D%5D%5D%5D&__client_imported__=true!",
          "async": false
        }
      },
      "layer": {
        "app/upload/page": "action-browser",
        "app/review/page": "action-browser"
      }
    },
    "002f4b96fa015b5e7631a93d678ccd881fbe444686": {
      "workers": {
        "app/debug/page": {
          "moduleId": "(action-browser)/./node_modules/next/dist/build/webpack/loaders/next-flight-action-entry-loader.js?actions=%5B%5B%22%2FUsers%2Frabibalam%2FDownloads%2Fapproved-main%2Fnode_modules%2F%40clerk%2Fnextjs%2Fdist%2Fesm%2Fapp-router%2Fserver-actions.js%22%2C%5B%7B%22id%22%3A%227fd62658a41224c9667c72a0b82c71390b1a333135%22%2C%22exportedName%22%3A%22invalidateCacheAction%22%7D%5D%5D%2C%5B%22%2FUsers%2Frabibalam%2FDownloads%2Fapproved-main%2Fsrc%2Factions%2Fdebug-actions.ts%22%2C%5B%7B%22id%22%3A%22002f4b96fa015b5e7631a93d678ccd881fbe444686%22%2C%22exportedName%22%3A%22testAIExtraction%22%7D%2C%7B%22id%22%3A%220033f2162d31a669790352a3a56b8afd96f4e4a15e%22%2C%22exportedName%22%3A%22debugDocuments%22%7D%5D%5D%2C%5B%22%2FUsers%2Frabibalam%2FDownloads%2Fapproved-main%2Fsrc%2Factions%2Fdebug-pdf.ts%22%2C%5B%7B%22id%22%3A%22002443ea3c5aaf566012ecc2982841d97404e5c95e%22%2C%22exportedName%22%3A%22debugPDFExtraction%22%7D%5D%5D%5D&__client_imported__=true!",
          "async": false
        }
      },
      "layer": {
        "app/debug/page": "action-browser"
      }
    },
    "0033f2162d31a669790352a3a56b8afd96f4e4a15e": {
      "workers": {
        "app/debug/page": {
          "moduleId": "(action-browser)/./node_modules/next/dist/build/webpack/loaders/next-flight-action-entry-loader.js?actions=%5B%5B%22%2FUsers%2Frabibalam%2FDownloads%2Fapproved-main%2Fnode_modules%2F%40clerk%2Fnextjs%2Fdist%2Fesm%2Fapp-router%2Fserver-actions.js%22%2C%5B%7B%22id%22%3A%227fd62658a41224c9667c72a0b82c71390b1a333135%22%2C%22exportedName%22%3A%22invalidateCacheAction%22%7D%5D%5D%2C%5B%22%2FUsers%2Frabibalam%2FDownloads%2Fapproved-main%2Fsrc%2Factions%2Fdebug-actions.ts%22%2C%5B%7B%22id%22%3A%22002f4b96fa015b5e7631a93d678ccd881fbe444686%22%2C%22exportedName%22%3A%22testAIExtraction%22%7D%2C%7B%22id%22%3A%220033f2162d31a669790352a3a56b8afd96f4e4a15e%22%2C%22exportedName%22%3A%22debugDocuments%22%7D%5D%5D%2C%5B%22%2FUsers%2Frabibalam%2FDownloads%2Fapproved-main%2Fsrc%2Factions%2Fdebug-pdf.ts%22%2C%5B%7B%22id%22%3A%22002443ea3c5aaf566012ecc2982841d97404e5c95e%22%2C%22exportedName%22%3A%22debugPDFExtraction%22%7D%5D%5D%5D&__client_imported__=true!",
          "async": false
        }
      },
      "layer": {
        "app/debug/page": "action-browser"
      }
    },
    "002443ea3c5aaf566012ecc2982841d97404e5c95e": {
      "workers": {
        "app/debug/page": {
          "moduleId": "(action-browser)/./node_modules/next/dist/build/webpack/loaders/next-flight-action-entry-loader.js?actions=%5B%5B%22%2FUsers%2Frabibalam%2FDownloads%2Fapproved-main%2Fnode_modules%2F%40clerk%2Fnextjs%2Fdist%2Fesm%2Fapp-router%2Fserver-actions.js%22%2C%5B%7B%22id%22%3A%227fd62658a41224c9667c72a0b82c71390b1a333135%22%2C%22exportedName%22%3A%22invalidateCacheAction%22%7D%5D%5D%2C%5B%22%2FUsers%2Frabibalam%2FDownloads%2Fapproved-main%2Fsrc%2Factions%2Fdebug-actions.ts%22%2C%5B%7B%22id%22%3A%22002f4b96fa015b5e7631a93d678ccd881fbe444686%22%2C%22exportedName%22%3A%22testAIExtraction%22%7D%2C%7B%22id%22%3A%220033f2162d31a669790352a3a56b8afd96f4e4a15e%22%2C%22exportedName%22%3A%22debugDocuments%22%7D%5D%5D%2C%5B%22%2FUsers%2Frabibalam%2FDownloads%2Fapproved-main%2Fsrc%2Factions%2Fdebug-pdf.ts%22%2C%5B%7B%22id%22%3A%22002443ea3c5aaf566012ecc2982841d97404e5c95e%22%2C%22exportedName%22%3A%22debugPDFExtraction%22%7D%5D%5D%5D&__client_imported__=true!",
          "async": false
        }
      },
      "layer": {
        "app/debug/page": "action-browser"
      }
    }
  },
  "edge": {},
  "encryptionKey": "E5PutqK6AGWVc7PYriq5ocqx251D7HvhY6JOhbLM5hE="
}